twitchircpy/__init__.py
twitchircpy/bot.py
twitchircpy/clearchat.py
twitchircpy/clearmsg.py
twitchircpy/command.py
twitchircpy/cooldown.py
twitchircpy/errors.py
twitchircpy/event.py
twitchircpy/general_notice.py
twitchircpy/hosttarget.py
twitchircpy/join_channel.py
twitchircpy/join_chatroom.py
twitchircpy/jtv_mode.py
twitchircpy/message.py
twitchircpy/part_channel.py
twitchircpy/roomstate.py
twitchircpy/timed_message.py
twitchircpy/usernotice.py
twitchircpy/userstate.py
twitchircpy/extensions/customcommandbot/__init__.py
twitchircpy/extensions/customcommandbot/chat_command.py
twitchircpy/extensions/customcommandbot/cooldown.py
twitchircpy/extensions/customcommandbot/customcommandbot.py
twitchircpy/extensions/customcommandbot/errors.py
twitchircpy/extensions/customcommandbot/variable.py
twitchircpy-1.0.5.dist-info/LICENSE
twitchircpy-1.0.5.dist-info/METADATA
twitchircpy-1.0.5.dist-info/WHEEL
twitchircpy-1.0.5.dist-info/top_level.txt
twitchircpy-1.0.5.dist-info/RECORD
