Metadata-Version: 2.1
Name: twitchircpy
Version: 1.0.5
Summary: A wrapper for the Twitch IRC used for creating chat bots.
Home-page: https://github.com/IsaacAKAJupiter/twitchircpy
Author: IsaacAKAJupiter
Author-email: oramisaac@gmail.com
License: UNKNOWN
Platform: UNKNOWN
Classifier: Development Status :: 3 - Alpha
Classifier: Programming Language :: Python :: 3
Classifier: Programming Language :: Python :: 3.7
Classifier: License :: OSI Approved :: GNU General Public License v3 (GPLv3)
Classifier: Operating System :: OS Independent
Classifier: Topic :: Internet
Classifier: Topic :: Software Development :: Libraries
Classifier: Topic :: Software Development :: Libraries :: Python Modules
Classifier: Topic :: Utilities
